vectordb_bench/__init__.py
vectordb_bench/__main__.py
vectordb_bench/base.py
vectordb_bench/interface.py
vectordb_bench/log_util.py
vectordb_bench/metric.py
vectordb_bench/models.py
vectordb_bench/backend/__init__.py
vectordb_bench/backend/assembler.py
vectordb_bench/backend/cases.py
vectordb_bench/backend/data_source.py
vectordb_bench/backend/dataset.py
vectordb_bench/backend/filter.py
vectordb_bench/backend/result_collector.py
vectordb_bench/backend/task_runner.py
vectordb_bench/backend/utils.py
vectordb_bench/backend/clients/__init__.py
vectordb_bench/backend/clients/api.py
vectordb_bench/backend/clients/alisql/alisql.py
vectordb_bench/backend/clients/alisql/cli.py
vectordb_bench/backend/clients/alisql/config.py
vectordb_bench/backend/clients/aliyun_elasticsearch/aliyun_elasticsearch.py
vectordb_bench/backend/clients/aliyun_elasticsearch/config.py
vectordb_bench/backend/clients/aliyun_opensearch/aliyun_opensearch.py
vectordb_bench/backend/clients/aliyun_opensearch/config.py
vectordb_bench/backend/clients/alloydb/alloydb.py
vectordb_bench/backend/clients/alloydb/cli.py
vectordb_bench/backend/clients/alloydb/config.py
vectordb_bench/backend/clients/aws_opensearch/aws_opensearch.py
vectordb_bench/backend/clients/aws_opensearch/cli.py
vectordb_bench/backend/clients/aws_opensearch/config.py
vectordb_bench/backend/clients/aws_opensearch/run.py
vectordb_bench/backend/clients/chroma/chroma.py
vectordb_bench/backend/clients/chroma/config.py
vectordb_bench/backend/clients/clickhouse/cli.py
vectordb_bench/backend/clients/clickhouse/clickhouse.py
vectordb_bench/backend/clients/clickhouse/config.py
vectordb_bench/backend/clients/cockroachdb/cli.py
vectordb_bench/backend/clients/cockroachdb/cockroachdb.py
vectordb_bench/backend/clients/cockroachdb/config.py
vectordb_bench/backend/clients/cockroachdb/db_retry.py
vectordb_bench/backend/clients/doris/cli.py
vectordb_bench/backend/clients/doris/config.py
vectordb_bench/backend/clients/doris/doris.py
vectordb_bench-1.0.18.dist-info/licenses/LICENSE
vectordb_bench-1.0.18.dist-info/METADATA
vectordb_bench-1.0.18.dist-info/WHEEL
vectordb_bench-1.0.18.dist-info/entry_points.txt
vectordb_bench-1.0.18.dist-info/top_level.txt
vectordb_bench-1.0.18.dist-info/RECORD
